tests/test_geo.py
tests/test_validators.py
tests/conftest.py
tests/test_validation.py
tests/test_files.py
tests/test_issue147.py
tests/urls.py
tests/test_router.py
tests/test_id.py
tests/test_compound.py
tests/test_embedded.py
tests/test_generics.py
tests/utils.py
tests/test_dynamic.py
tests/test_reference.py
tests/mockpil.py
tests/models.py
tests/test_basic.py
tests/test_fields.py
tests/test_patching.py
tests/__init__.py
tests/test_dumb.py
rest_framework_mongoengine/validators.py
rest_framework_mongoengine/repr.py
rest_framework_mongoengine/fields.py
rest_framework_mongoengine/utils.py
rest_framework_mongoengine/serializers.py
rest_framework_mongoengine/routers.py
rest_framework_mongoengine/generics.py
rest_framework_mongoengine/__init__.py
rest_framework_mongoengine/viewsets.py
rest_framework_mongoengine/contrib/patching.py
rest_framework_mongoengine/contrib/__init__.py
django_rest_framework_mongoengine-3.3.1.dist-info/metadata.json
django_rest_framework_mongoengine-3.3.1.dist-info/METADATA
django_rest_framework_mongoengine-3.3.1.dist-info/DESCRIPTION.rst
django_rest_framework_mongoengine-3.3.1.dist-info/top_level.txt
django_rest_framework_mongoengine-3.3.1.dist-info/WHEEL
django_rest_framework_mongoengine-3.3.1.dist-info/RECORD
